{
  "exptype": "meta_test",
  "ckpt_path": "experiments/meta_test/metamultiplicative/version_1",
  "checkpt": "None",
  "gpus": [0],

  "model": "metamultiplicative",

  "metrics": [
    "recon_mse"
  ],

  "func_type": "multiplicative",

  "meta": true,
  "num_tasks": 5,
  "k_shot": 3,

  "timesteps": 20,
  "num_samples": 100,
  "num_epochs": 350,
  "check_every_n_steps": 50,


  "batch_size": 25,
  "learning_rate": 1e-3,

  "in_dim": 1,
  "control_dim": 1,
  "hidden_dim": 32,
  "out_dim": 1,

  "latent_act": "swish"
}
